sadf/__init__.py
sadf/fieldgroups.py
sadf-0.1.2.dist-info/LICENSE
sadf-0.1.2.dist-info/METADATA
sadf-0.1.2.dist-info/WHEEL
sadf-0.1.2.dist-info/top_level.txt
sadf-0.1.2.dist-info/RECORD
