Metadata-Version: 2.1
Name: sadf
Version: 0.1.2
Summary: Parse sysstat (sa/sar) output into Pandas Dataframes
Home-page: http://github.com/jpgxs/python-sadf
Author: Joshua Griffiths
Author-email: jgriffiths@x86-64.io
License: UNKNOWN
Platform: POSIX
Classifier: Development Status :: 3 - Alpha
Classifier: Intended Audience :: Developers
Classifier: Intended Audience :: System Administrators
Classifier: License :: OSI Approved :: Apache Software License
Classifier: Operating System :: POSIX :: Linux
Classifier: Programming Language :: Python
Classifier: Programming Language :: Python :: 2
Classifier: Programming Language :: Python :: 2.6
Classifier: Programming Language :: Python :: 2.7
Classifier: Programming Language :: Python :: 3
Classifier: Programming Language :: Python :: 3.0
Classifier: Programming Language :: Python :: 3.1
Classifier: Programming Language :: Python :: 3.2
Classifier: Programming Language :: Python :: 3.3
Classifier: Programming Language :: Python :: 3.4
Classifier: Programming Language :: Python :: 3.5
Requires-Dist: dateparser (>=0.4.0)
Requires-Dist: pandas (>=0.18.0)
Requires-Dist: pytz
Requires-Dist: six (>=1.0.0)
Requires-Dist: tzlocal (>=1.0.0)
Requires-Dist: simplejson
